wifitx.py
wifitx-0.5.0.dist-info/DESCRIPTION.rst
wifitx-0.5.0.dist-info/METADATA
wifitx-0.5.0.dist-info/RECORD
wifitx-0.5.0.dist-info/WHEEL
wifitx-0.5.0.dist-info/entry_points.txt
wifitx-0.5.0.dist-info/metadata.json
wifitx-0.5.0.dist-info/top_level.txt
