Metadata-Version: 2.0
Name: wifitx
Version: 0.5.0
Summary: Command line interface for testing wifi transmission speed
Home-page: https://github.com/nickever/wifi-TxRate
Author: Nick Everett
Author-email: njeverett@gmail.com
License: GNU General Public License v3.0
Keywords: wifi test speed transmission tx wifitx
Platform: macOS
Classifier: Programming Language :: Python
Classifier: Development Status :: 3 - Alpha
Classifier: Natural Language :: English
Classifier: Environment :: Console
Classifier: License :: OSI Approved :: GNU General Public License v3 (GPLv3)
Classifier: Operating System :: MacOS :: MacOS X
Classifier: Programming Language :: Python :: 3
Classifier: Programming Language :: Python :: 3.1
Classifier: Programming Language :: Python :: 3.2
Classifier: Programming Language :: Python :: 3.3
Classifier: Programming Language :: Python :: 3.4
Classifier: Programming Language :: Python :: 3.5
Classifier: Topic :: System :: Networking
